sql_generator/__init__.py
sql_generator/analyser.py
sql_generator/data_type_generators.py
sql_generator/extra_generators.py
sql_generator/formatters.py
sql_generator/generator.py
sql_generator/resources/first.txt
sql_generator/resources/last.txt
sql_generator/utils.py
sql_generator-0.2.0.dist-info/WHEEL
sql_generator-0.2.0.dist-info/METADATA
sql_generator-0.2.0.dist-info/RECORD
